{
	"configurations" : 
	[
		{
			"directories" : 
			[
				{
					"build" : ".",
					"jsonFile" : "directory-.-Debug-d0094a50bb2071803777.json",
					"minimumCMakeVersion" : 
					{
						"string" : "3.27"
					},
					"projectIndex" : 0,
					"source" : ".",
					"targetIndexes" : 
					[
						0
					]
				}
			],
			"name" : "Debug",
			"projects" : 
			[
				{
					"directoryIndexes" : 
					[
						0
					],
					"name" : "c_dataframe_ndouga_rakotoarinia_e",
					"targetIndexes" : 
					[
						0
					]
				}
			],
			"targets" : 
			[
				{
					"directoryIndex" : 0,
					"id" : "c_dataframe_ndouga_rakotoarinia_e::@6890427a1f51a3e7e1df",
					"jsonFile" : "target-c_dataframe_ndouga_rakotoarinia_e-Debug-946f4e9fbcfb38b78490.json",
					"name" : "c_dataframe_ndouga_rakotoarinia_e",
					"projectIndex" : 0
				}
			]
		}
	],
	"kind" : "codemodel",
	"paths" : 
	{
		"build" : "C:/Users/Kimberley/CLionProjects/c-dataframe-ndouga-rakotoarinia-e/cmake-build-debug",
		"source" : "C:/Users/Kimberley/CLionProjects/c-dataframe-ndouga-rakotoarinia-e"
	},
	"version" : 
	{
		"major" : 2,
		"minor" : 6
	}
}
